dduk/__init__.py
dduk/__main__.py
dduk/core/__init__.py
dduk/core/__main__.py
dduk/core/anonymousclass.py
dduk/core/baseclass.py
dduk/core/basemetaclass.py
dduk/core/baserepository.py
dduk/core/builtins.py
dduk/core/constant.py
dduk/core/decorator.py
dduk/core/environment.py
dduk/core/node.py
dduk/core/path.py
dduk/core/sharedclass.py
dduk/core/singleton.py
dduk_core-0.0.41.dist-info/LICENSE
dduk_core-0.0.41.dist-info/METADATA
dduk_core-0.0.41.dist-info/WHEEL
dduk_core-0.0.41.dist-info/top_level.txt
dduk_core-0.0.41.dist-info/RECORD
